bqcli/__init__.py
bqcli-0.1.3.dist-info/METADATA
bqcli-0.1.3.dist-info/WHEEL
bqcli-0.1.3.dist-info/entry_points.txt
bqcli-0.1.3.dist-info/licenses/LICENSE.md
bqcli-0.1.3.dist-info/RECORD
