Metadata-Version: 2.4
Name: bqcli
Version: 0.1.3
Summary: REPL for BigQuery
Author-email: Jan Červenka <jan.cervenka@yahoo.com>
License-File: LICENSE.md
Requires-Python: >=3.12
Requires-Dist: google-cloud-bigquery>=3.27.0
Requires-Dist: pandas>=2.2.3
Requires-Dist: prompt-toolkit>=3.0.48
Requires-Dist: pygments>=2.18.0
